{
  "swagger" : "2.0",
  "info" : {
    "title" : "UpdateContractTemplateDetails",
    "version" : "1.0.0",
    "description" : "This service is used to update contract template details."
  },
  "paths" : {
    "/updatecontracttemplatedetails" : {
      "post" : {
        "operationId" : "UpdateContractTemplateDetails",
        "responses" : {
          "200" : {
            "description" : "The operation was successful.",
            "schema" : {
              "$ref" : "#/definitions/UpdateContractTemplateDetailsRs_MessageType"
            }
          }
        },
        "consumes" : [ "application/json" ],
        "produces" : [ "application/json" ],
        "description" : "Update Contract Template Details",
        "parameters" : [ {
          "name" : "body",
          "in" : "body",
          "schema" : {
            "$ref" : "#/definitions/UpdateContractTemplateDetailsRq_MessageType"
          },
          "description" : "UpdateContractTemplateDetailsRq",
          "required" : true
        } ]
      }
    }
  },
  "basePath" : "/contractmanagement",
  "definitions" : {
    "UpdateContractTemplateDetailsRq_MessageType" : {
      "type" : "object",
      "properties" : {
        "UpdateContractTemplateDetailsRq" : {
          "$ref" : "#/definitions/UpdateContractTemplateDetailsRq_Type"
        }
      }
    },
    "UpdateContractTemplateDetailsRs_MessageType" : {
      "type" : "object",
      "properties" : {
        "UpdateContractTemplateDetailsRs" : {
          "$ref" : "#/definitions/UpdateContractTemplateDetailsRs_Type"
        }
      }
    },
    "UpdateContractTemplateDetailsRq_Type" : {
      "type" : "object",
      "properties" : {
        "Header" : {
          "$ref" : "#/definitions/ESBXMLRequestHeader_Type"
        },
        "Body" : {
          "$ref" : "#/definitions/UpdateContractTemplateDetailsRq_BodyType"
        }
      }
    },
    "UpdateContractTemplateDetailsRq_BodyType" : {
      "type" : "object",
      "properties" : {
        "TemplateId" : {
          "type" : "integer"
        },
        "ClausesList" : {
          "$ref" : "#/definitions/ClausesList_Type"
        },
        "EstablishmentDetails" : {
          "$ref" : "#/definitions/EstablishmentDetails_Type"
        },
        "LaborerDetails" : {
          "$ref" : "#/definitions/LaborerDetails_Type"
        },
        "RequesterDetails" : {
          "$ref" : "#/definitions/RequesterDetails_type"
        },
        "ContractDetails" : {
          "$ref" : "#/definitions/ContractDetails_Type"
        },
        "LanguageId" : {
          "type" : "integer"
        },
        "TemplateName" : {
          "type" : "string"
        },
        "TemplateDescription" : {
          "type" : "string"
        },
        "DateTypeId" : {
          "type" : "integer"
        }
      },
      "required" : [ "TemplateId", "EstablishmentDetails" ]
    },
    "ClausesList_Type" : {
      "type" : "object",
      "properties" : {
        "AddedClauses" : {
          "$ref" : "#/definitions/KeyValue_Type"
        },
        "Allowances" : {
          "$ref" : "#/definitions/KeyValue_Type"
        }
      }
    },
    "UpdateContractTemplateDetailsRs_Type" : {
      "type" : "object",
      "properties" : {
        "Header" : {
          "$ref" : "#/definitions/ESBXMLResponseHeader_Type"
        },
        "Body" : {
          "$ref" : "#/definitions/UpdateContractTemplateDetailsRs_BodyType"
        }
      }
    },
    "UpdateContractTemplateDetailsRs_BodyType" : { },
    "ESBXMLRequestHeader_Type" : {
      "type" : "object",
      "properties" : {
        "TransactionId" : {
          "type" : "string"
        },
        "ChannelId" : {
          "type" : "string"
        },
        "SessionId" : {
          "type" : "string"
        },
        "RequestTime" : {
          "type" : "string"
        },
        "MWRequestTime" : {
          "type" : "string"
        },
        "ServiceCode" : {
          "type" : "string"
        },
        "DebugFlag" : {
          "type" : "integer"
        },
        "UserInfo" : {
          "$ref" : "#/definitions/UserInfo_Type"
        },
        "UDF" : {
          "$ref" : "#/definitions/UDF_Type"
        }
      },
      "required" : [ "ServiceCode", "ChannelId", "TransactionId", "RequestTime" ]
    },
    "ESBXMLResponseHeader_Type" : {
      "type" : "object",
      "properties" : {
        "TransactionId" : {
          "type" : "string"
        },
        "ChannelId" : {
          "type" : "string"
        },
        "SessionId" : {
          "type" : "string"
        },
        "RequestTime" : {
          "type" : "string"
        },
        "MWRequestTime" : {
          "type" : "string"
        },
        "MWResponseTime" : {
          "type" : "string"
        },
        "ServiceCode" : {
          "type" : "string"
        },
        "DebugFlag" : {
          "type" : "integer"
        },
        "UserInfo" : {
          "$ref" : "#/definitions/UserInfo_Type"
        },
        "UDF" : {
          "$ref" : "#/definitions/UDF_Type"
        },
        "ResponseStatus" : {
          "$ref" : "#/definitions/MWResponseStatus_Type"
        },
        "BackendError" : {
          "$ref" : "#/definitions/BackendError_Type"
        }
      },
      "required" : [ "TransactionId", "ChannelId", "RequestTime", "ServiceCode" ]
    },
    "UDF_Type" : {
      "type" : "object",
      "properties" : {
        "KeyValueArr" : {
          "type" : "array",
          "items" : {
            "$ref" : "#/definitions/KeyValueArr_Type"
          }
        }
      }
    },
    "KeyValueArr_Type" : {
      "type" : "object",
      "properties" : {
        "key" : {
          "type" : "string"
        },
        "value" : {
          "type" : "string"
        }
      }
    },
    "Tmstmp_Type" : {
      "type" : "object"
    },
    "UserInfo_Type" : {
      "type" : "object",
      "properties" : {
        "UserId" : {
          "type" : "integer"
        },
        "IDNumber" : {
          "type" : "integer"
        }
      }
    },
    "MWResponseStatus_Type" : {
      "type" : "object",
      "properties" : {
        "Status" : {
          "type" : "string"
        },
        "Code" : {
          "type" : "string"
        },
        "ArabicMsg" : {
          "type" : "string"
        },
        "EnglishMsg" : {
          "type" : "string"
        }
      },
      "required" : [ "Code", "Status", "ArabicMsg", "EnglishMsg" ]
    },
    "BackendError_Type" : {
      "type" : "object",
      "properties" : {
        "ErrorCode" : {
          "type" : "string"
        },
        "ErrorDescription" : {
          "type" : "string"
        }
      }
    },
    "EstablishmentDetails_Type" : {
      "type" : "object",
      "properties" : {
        "LaborOfficeId" : {
          "type" : "integer"
        },
        "SequenceNumber" : {
          "type" : "integer"
        },
        "EstablishmentId" : {
          "type" : "integer"
        },
        "UnifiedNumberId" : {
          "type" : "integer"
        },
        "EntityId" : {
          "type" : "string"
        },
        "EstablishmentNameAr" : {
          "type" : "string"
        },
        "EstablishmentNameEn" : {
          "type" : "string"
        },
        "EstablishmentEmail" : {
          "type" : "string"
        }
      },
      "required" : [ "LaborOfficeId", "SequenceNumber" ]
    },
    "LaborerDetails_Type" : {
      "type" : "object",
      "properties" : {
        "LaborerIdNo" : {
          "type" : "integer"
        },
        "LaborerName" : {
          "type" : "string"
        },
        "LaborerTypeId" : {
          "type" : "integer"
        },
        "LaborerIdExpiryDate" : {
          "type" : "string"
        },
        "LaborerEmail" : {
          "type" : "string"
        },
        "LaborerMobileNumber" : {
          "type" : "integer"
        }
      }
    },
    "RequesterDetails_type" : {
      "type" : "object",
      "properties" : {
        "RequesterIdNo" : {
          "type" : "integer"
        },
        "RequesterName" : {
          "type" : "string"
        },
        "RequesterUserId" : {
          "type" : "integer"
        }
      }
    },
    "JobTitle_Type" : {
      "type" : "object",
      "properties" : {
        "JobTitleAr" : {
          "type" : "string"
        },
        "JobTitleEng" : {
          "type" : "string"
        }
      }
    },
    "HGDate_Type" : {
      "type" : "object",
      "properties" : {
        "HijriDate" : {
          "type" : "integer"
        },
        "GregDate" : {
          "type" : "string"
        }
      }
    },
    "AdditionalAllowancesList_Type" : {
      "type" : "object",
      "properties" : {
        "Item" : {
          "type" : "array",
          "items" : {
            "$ref" : "#/definitions/Item_Type"
          }
        }
      },"required" : [ "Item"]
    },
    "Item_Type" : {
      "type" : "object",
      "properties" : {
        "BenefitNameAr" : {
          "type" : "string"
        },
        "BenefitNameEn" : {
          "type" : "string"
        },
        "Frequency" : {
          "type" : "integer"
        },
        "AmountType" : {
          "type" : "integer"
        },
        "Amount" : {
          "type" : "number"
        }
      }
    },
    "OptionalArticles_Type" : {
      "type" : "object",
      "properties" : {
        "Period" : {
          "type" : "integer"
        },
        "Location" : {
          "type" : "string"
        },
        "WorkField" : {
          "type" : "string"
        }
      }
    },
    "ContractDetails_Type" : {
      "type" : "object",
      "properties" : {
        "JobTitle" : {
          "$ref" : "#/definitions/JobTitle_Type"
        },
        "LaborerJobNumber" : {
          "type" : "integer"
        },
        "ContractTypeId" : {
          "type" : "integer"
        },
        "ContractDurationId" : {
          "type" : "integer"
        },
        "ContractPeriod" : {
          "type" : "integer"
        },
        "ProbationPeriod" : {
          "type" : "integer"
        },
        "ProbationTerminationRight" : {
          "type" : "integer",
          "enum": [1, 2, 3]
        },
        "WorkingHoursTypeId" : {
          "type" : "integer"
        },
        "VacationPeriod" : {
          "type" : "integer"
        },
        "Salary" : {
          "type" : "number"
        },
        "SalaryTypeId" : {
            "type" : "integer"
          },
        "PercentageReasonEN" : {
              "type" : "string"
         }, 
         "PercentageReasonAR" : {
             "type" : "string"
        },
        "StartDate" : {
          "$ref" : "#/definitions/HGDate_Type"
        },
        "ExpiryDate" : {
          "$ref" : "#/definitions/HGDate_Type"
        },
        "RenewalStatusId" : {
          "type" : "integer"
        },
        "NoticePeriod" : {
          "type" : "integer"
        },
        "SalaryFrequency" : {
          "type" : "integer"
        },
        "AdditionalAllowancesList" : {
          "$ref" : "#/definitions/AdditionalAllowancesList_Type"
        },
        "HoursPerWeek" : {
          "type" : "integer"
        },
        "DaysPerWeek" : {
          "type" : "integer"
        },
        "HoursPerDay" : {
          "type" : "integer"
        },
        "OptionalArticles" : {
          "$ref" : "#/definitions/OptionalArticles_Type"
        }
      },"required" : [ "SalaryTypeId"]
    },
    "KeyValue_Type" : {
      "type" : "object",
      "properties" : {
        "Key" : {
          "type" : "string"
        },
        "Value" : {
          "type" : "string"
        }
      }
    }
  }
}