{
  "swagger" : "2.0",
  "info" : {
    "title" : "CheckTCLaborerEligibility",
    "version" : "1.0.0",
    "description" : "CheckTCLaborerEligibility"
  },
  "paths" : {
    "/checktclabelig" : {
      "post" : {
        "operationId" : "CheckTCLaborerEligibility",
        "responses" : {
          "200" : {
            "description" : "The operation was successful.",
            "schema" : {
              "$ref" : "#/definitions/CheckTCLaborerEligibilityRs_MessageType"
            }
          }
        },
        "consumes" : [ "application/json" ],
        "produces" : [ "application/json" ],
        "description" : "Check TC Laborer Eligibility",
        "parameters" : [ {
          "name" : "body",
          "in" : "body",
          "schema" : {
            "$ref" : "#/definitions/CheckTCLaborerEligibilityRq_MessageType"
          },
          "description" : "CheckTCLaborerEligibilityRq",
          "required" : true
        } ]
      }
    }
  },
  "basePath" : "/tc",
  "definitions" : {
    "CheckTCLaborerEligibilityRq_MessageType" : {
      "type" : "object",
      "properties" : {
        "CheckTCLaborerEligibilityRq" : {
          "$ref" : "#/definitions/CheckTCLaborerEligibilityRq_Type"
        }
      }
    },
    "CheckTCLaborerEligibilityRs_MessageType" : {
      "type" : "object",
      "properties" : {
        "CheckTCLaborerEligibilityRs" : {
          "$ref" : "#/definitions/CheckTCLaborerEligibilityRs_Type"
        }
      }
    },
    "CheckTCLaborerEligibilityRq_Type" : {
      "type" : "object",
      "properties" : {
        "Header" : {
          "$ref" : "#/definitions/ESBXMLRequestHeader_Type"
        },
        "Body" : {
          "$ref" : "#/definitions/CheckTCLaborerEligibilityRq_BodyType"
        }
      }
    },
    "CheckTCLaborerEligibilityRq_BodyType" : {
      "type" : "object",
      "properties" : {
       
        "RequesterTypeId" : {
          "type" : "integer"
        },
		
        "LaborerTypeId" : {
	          "type" : "integer"
	        },
			"HasPendingTCRequest" : {
				"type" : "boolean"
			},
			"HasActiveContract" : {
		          "type" : "boolean"
		        },
				"HasContractOnSystem" : {
		          "type" : "boolean"
		        },
				 "LaborerStatusCode" : {
          "type" : "integer"
        },
		"EntryDate" : {
		          "type" : "string"
		        },
				"HasPendingCSRequest" : {
		          "type" : "boolean"
		        }
				
				
		},
		
		"required" : ["RequesterTypeId","LaborerTypeId","HasPendingTCRequest","HasActiveContract"]
  },
   
 
    "CheckTCLaborerEligibilityRs_Type" : {
      "type" : "object",
      "properties" : {
        "Header" : {
          "$ref" : "#/definitions/ESBXMLResponseHeader_Type"
        },
        "Body" : {
          "$ref" : "#/definitions/CheckTCLaborerEligibilityRs_BodyType"
        }
      }
    },
    "CheckTCLaborerEligibilityRs_BodyType" : {
      "type" : "object",
      "properties" : {
      "ErrorsList ":{
	  "$ref":"#/definitions/ErrorList_Type"
	  }
	  
      }
    },
	"ErrorList_Type" : {
		"type" : "object",
		"properties" : {
			"Error" : {
		          "type" : "array" ,
		          "items" :{ 
		        	  "$ref" : "#/definitions/Error_Type"

		            }
		        }
			
		}
	},
	"Error_Type" : {
		"type" : "object",
		"properties" : {
			"ErrorCode" : {
				"type" : "integer"
			},
			"ArDescription" : {
				"type" : "string"
			},
			"EngDescription" : {
				"type" : "string"
			}
		},
		"required" : ["ErrorCode" , "ArDescription" , "EngDescription"]
	},
	
  
    "ESBXMLRequestHeader_Type" : {
      "type" : "object",
      "properties" : {
        "TransactionId" : {
          "type" : "string"
        },
        "ChannelId" : {
          "type" : "string"
        },
        "SessionId" : {
          "type" : "string"
        },
        "RequestTime" : {
          "type" : "string"
        },
        "MWRequestTime" : {
          "type" : "string"
        },
        "ServiceCode" : {
          "type" : "string"
        },
        "DebugFlag" : {
          "type" : "integer"
        },
        "UserInfo" : {
          "$ref" : "#/definitions/UserInfo_Type"
        },
        "UDF" : {
          "$ref" : "#/definitions/UDF_Type"
        }
      },
      "required" : [ "ServiceCode", "ChannelId", "TransactionId", "RequestTime" ]
    },
    "ESBXMLResponseHeader_Type" : {
      "type" : "object",
      "properties" : {
        "TransactionId" : {
          "type" : "string"
        },
        "ChannelId" : {
          "type" : "string"
        },
        "SessionId" : {
          "type" : "string"
        },
        "RequestTime" : {
          "type" : "string"
        },
        "MWRequestTime" : {
          "type" : "string"
        },
        "MWResponseime" : {
          "type" : "string"
        },
        "ServiceCode" : {
          "type" : "string"
        },
        "DebugFlag" : {
          "type" : "integer"
        },
        "UserInfo" : {
          "$ref" : "#/definitions/UserInfo_Type"
        },
        "UDF" : {
          "$ref" : "#/definitions/UDF_Type"
        },
        "ResponseStatus" : {
          "$ref" : "#/definitions/MWResponseStatus_Type"
        },
        "BackendError" : {
          "$ref" : "#/definitions/BackendError_Type"
        }
      },
      "required" : [ "TransactionId", "ChannelId", "RequestTime", "ServiceCode" ]
    },
    "UDF_Type" : {
      "type" : "object",
      "properties" : {
        "KeyValueArr" : {
          "type" : "array",
          "items" : {
            "$ref" : "#/definitions/KeyValueArr_Type"
          }
        }
      }
    },
    "KeyValueArr_Type" : {
      "type" : "object",
      "properties" : {
        "key" : {
          "type" : "string"
        },
        "value" : {
          "type" : "string"
        }
      }
    },
    "Tmstmp_Type" : {
      "type" : "object"
    },
    "UserInfo_Type" : {
      "type" : "object",
      "properties" : {
        "UserId" : {
          "type" : "integer"
        },
        "IDNumber" : {
          "type" : "integer"
        }
      }
    },
    "MWResponseStatus_Type" : {
      "type" : "object",
      "properties" : {
        "Status" : {
          "type" : "string"
        },
        "Code" : {
          "type" : "string"
        },
        "ArabicMsg" : {
          "type" : "string"
        },
        "EnglishMsg" : {
          "type" : "string"
        }
      },
      "required" : [ "Code", "Status", "ArabicMsg", "EnglishMsg" ]
    },
    "BackendError_Type" : {
      "type" : "object",
      "properties" : {
        "ErrorCode" : {
          "type" : "string"
        },
        "ErrorDescription" : {
          "type" : "string"
        }
      }
    }
  }
}